sim_rl/.gitlab-ci.yml
sim_rl/__init__.py
sim_rl/agents/__init__.py
sim_rl/agents/buffer.py
sim_rl/agents/ddpg_agent.py
sim_rl/agents/model.py
sim_rl/agents/trained_agent.pt
sim_rl/agents/trained_ddpg_agent.pt
sim_rl/debug.py
sim_rl/dist/sim_rl-0.1.0.tar.gz
sim_rl/evaluation/__init__.py
sim_rl/evaluation/convergence_evaluation/__init__.py
sim_rl/evaluation/convergence_evaluation/convergence_evaluation.py
sim_rl/evaluation/convergence_evaluation/reward_plot.png
sim_rl/evaluation/decision_evaluation/__init__.py
sim_rl/evaluation/decision_evaluation/decision_evaluation.py
sim_rl/evaluation/decision_evaluation/output_plots/Transition_Proba_BeforeAfter_Blockage.png
sim_rl/evaluation/noise_evaluation/__init__.py
sim_rl/evaluation/noise_evaluation/noise_evaluation.py
sim_rl/evaluation/robustness_evaluation/__init__.py
sim_rl/evaluation/robustness_evaluation/robustness_evaluation.py
sim_rl/evaluation/startup_evaluation/.gitkeep
sim_rl/evaluation/startup_evaluation/__init__.py
sim_rl/evaluation/startup_evaluation/reward_plot.png
sim_rl/evaluation/startup_evaluation/reward_plot_0.png
sim_rl/evaluation/startup_evaluation/reward_plot_1.png
sim_rl/evaluation/startup_evaluation/reward_plot_2.png
sim_rl/evaluation/startup_evaluation/reward_plot_3.png
sim_rl/evaluation/startup_evaluation/startup_evaluation.py
sim_rl/foundations/__init__.py
sim_rl/foundations/breakdown_exploration/__init__.py
sim_rl/foundations/breakdown_exploration/breakdown_exploration.py
sim_rl/foundations/breakdown_exploration/output_data/all_breakdown_cases.json
sim_rl/foundations/breakdown_exploration/output_data/coverage_metric/coverage.json
sim_rl/foundations/breakdown_exploration/output_data/key_states/key_states.json
sim_rl/foundations/breakdown_exploration/output_data/key_states/rewards.png
sim_rl/foundations/breakdown_exploration/output_data/peripheral_states/peripheral_states.json
sim_rl/foundations/breakdown_exploration/output_data/peripheral_states/visits.png
sim_rl/foundations/core_functions.py
sim_rl-0.1.9.dist-info/METADATA
sim_rl-0.1.9.dist-info/WHEEL
sim_rl-0.1.9.dist-info/RECORD
