Metadata-Version: 2.1
Name: sim_rl
Version: 0.1.9
Summary: Simulation Driven RL Package Utilized to Optimize Queueing Systems
Author: Fatima Alani, Jinyan Wang, Jevon Charles, Joshua Forday, Aaron Ong, Vinayak Modi
Author-email: fatima.al-ani23@imperial.ac.uk
Requires-Python: >=3.10,<3.12
Classifier: Programming Language :: Python :: 3
Classifier: Programming Language :: Python :: 3.10
Classifier: Programming Language :: Python :: 3.11
Requires-Dist: PyYAML (==6.0.1)
Requires-Dist: matplotlib (==3.8.3)
Requires-Dist: numpy (==1.26.4)
Requires-Dist: pandas (==2.2.0)
Requires-Dist: queueing_tool (==1.2.5)
Requires-Dist: ray[train,tune] (==2.9.2)
Requires-Dist: scipy (==1.12.0)
Requires-Dist: torch (==2.2.0)
Requires-Dist: tqdm (==4.57.0)
Requires-Dist: wandb (==0.16.3)
